mia21/__init__.py
mia21/client.py
mia21/exceptions.py
mia21/models.py
mia21/portal_client.py
mia21-1.3.1.dist-info/licenses/LICENSE
mia21-1.3.1.dist-info/METADATA
mia21-1.3.1.dist-info/WHEEL
mia21-1.3.1.dist-info/top_level.txt
mia21-1.3.1.dist-info/RECORD
